LICENSE
README.rst
pyproject.toml
setup.py
docs/source/conf.py
lensless/__init__.py
lensless/version.py
lensless.egg-info/PKG-INFO
lensless.egg-info/SOURCES.txt
lensless.egg-info/dependency_links.txt
lensless.egg-info/requires.txt
lensless.egg-info/top_level.txt
lensless/eval/__init__.py
lensless/eval/benchmark.py
lensless/eval/metric.py
lensless/hardware/__init__.py
lensless/hardware/aperture.py
lensless/hardware/constants.py
lensless/hardware/fabrication.py
lensless/hardware/mask.py
lensless/hardware/sensor.py
lensless/hardware/slm.py
lensless/hardware/trainable_mask.py
lensless/hardware/utils.py
lensless/recon/__init__.py
lensless/recon/admm.py
lensless/recon/apgd.py
lensless/recon/gd.py
lensless/recon/integrated_background_sub.py
lensless/recon/mirflickr.py
lensless/recon/model_dict.py
lensless/recon/multi_wiener.py
lensless/recon/recon.py
lensless/recon/restormer.py
lensless/recon/rfft_convolve.py
lensless/recon/sv_deconvnet.py
lensless/recon/tikhonov.py
lensless/recon/trainable_inversion.py
lensless/recon/trainable_recon.py
lensless/recon/unrolled_admm.py
lensless/recon/unrolled_fista.py
lensless/recon/utils.py
lensless/recon/drunet/basicblock.py
lensless/recon/drunet/network_unet.py
lensless/utils/__init__.py
lensless/utils/dataset.py
lensless/utils/image.py
lensless/utils/io.py
lensless/utils/plot.py
lensless/utils/simulation.py
profile/admm.py
profile/diffusercam_admm.py
profile/diffusercam_gd.py
profile/gradient_descent.py
scripts/demo.py
scripts/classify/train_celeba_vit.py
scripts/data/plot_psf.py
scripts/data/prepare_mirflickr_subset.py
scripts/data/rename_mirflickr25k.py
scripts/data/upload_dataset_huggingface.py
scripts/data/upload_diffusercam_huggingface.py
scripts/data/3d/mat_to_npy.py
scripts/data/3d/mat_to_npz.py
scripts/data/3d/npy_to_obj.py
scripts/data/3d/npy_to_tiff.py
scripts/demo/telegram_bot.py
scripts/eval/benchmark_recon.py
scripts/eval/compute_metrics_from_original.py
scripts/hardware/config_digicam.py
scripts/hardware/digicam_measure_psfs.py
scripts/hardware/digicam_psf_stats.py
scripts/hardware/set_digicam_mask_distance.py
scripts/measure/analyze_image.py
