Metadata-Version: 2.1
Name: lensless
Version: 1.0.8
Summary: All-in-one package for lensless imaging: design, simulation, measurement, reconstruction.
Home-page: https://github.com/LCAV/LenslessPiCam
Author: Eric Bezzam
Author-email: ebezzam@gmail.com
Classifier: Programming Language :: Python :: 3
Classifier: Operating System :: OS Independent
Requires-Python: >=3.8.1, <3.12
License-File: LICENSE
